src/memFile.v


module memory_io(

    input clk,
    input reset,

    // Señales de control
    input memRead,
    input memWrite,

    // Dirección desde la ALU
    input [31:0] address,

    // Dato desde el Register File
    input [31:0] write_data,
    input [31:0] ins,               //To detect ret and memDump.

    // Dato leído hacia Write Back
    output reg [31:0] read_data
    
);

    // Memoria de datos
    reg [31:0] data_memory [0:255];

    integer i;

    // ============================================
    // RESET + ESCRITURA
    // ============================================

    always @(posedge clk) begin

        if (reset) begin

            

            for(i = 0; i < 256; i = i + 1)
                data_memory[i] <= 32'b0;
            data_memory[10] <= 32'hDEADBEEF;

        end

        else if(memWrite) begin

            case(address)

                

                // Memoria normal
                default:
                    data_memory[address[9:2]] <= write_data;

            endcase
        end
    end

    // ============================================
    // LECTURA COMBINACIONAL
    // ============================================

    always @(*) begin

        if(memRead) begin

            case(address)

                

                // Memoria normal
                default:
                    read_data = data_memory[address[9:2]];

            endcase
        end

        else begin
            read_data = 32'b0;
        end
    end



    //Finish sim and memDump Logic
    integer fd;
    always @(posedge clk) begin
        if (ins == 32'h00008067) begin
            $display("=== Memory Dump ===");
            fd = $fopen("./memDump.hex", "w");
            for (i = 0; i < 256; i = i + 1) begin
                $fdisplay(fd, "%08h:%08h", i*4, data_memory[i]);
            end
            $fclose(fd);
            $finish;
        end
    end

endmodule

src/alu.v


module ALU(
	input wire [31:0] inA,
	input wire [31:0] inB,
	input wire [3:0]  aluControl,

	output wire [31:0] result,
	output wire [0:0] zero,
	output wire [0:0] carry,	//Tied to zero cause fuck this
	output wire [0:0] negative,
	output wire [0:0] overflow
	);

	
	wire [31:0] sumW;
	wire [31:0] subW;
	wire [31:0] llsW;
	wire [31:0] lrsW;
	wire [31:0] arsW;
	wire [31:0] sltW;
	wire [31:0] sluW;
	wire [31:0] andW;
	wire [31:0] _orW;
	wire [31:0] xorW;


	reg [31:0] tOut;
	assign result = overflow ? 32'b0:tOut;

	assign sumW = inA+inB;
	assign subW = inA-inB;
	assign llsW = inA<<inB[4:0];
	assign lrsW = inA>>inB[4:0];
	assign arsW = $signed(inA)>>>inB[4:0];
	assign sltW = ($signed(inA)<$signed(inB)) ? 32'b1 : 32'b0;
	assign sluW = (inA<inB) ? 32'b1 : 32'b0;
	assign andW = inA & inB;
	assign _orW = inA | inB;
	assign xorW = inA ^ inB;
	
	assign zero = ~(|tOut);
	assign carry = 0;
	assign negative = tOut[31];
	assign overflow = aluControl==ADD?(inA[31]^tOut[31]&(inB[31]^tOut[31])):0;




	always @(*) begin
		case(aluControl)
			ADD: tOut=sumW;
			SUB: tOut=subW;
			LLS: tOut=llsW;
			LRS: tOut=lrsW;
			ARS: tOut=arsW;
			SLT: tOut=sltW;
			SLU: tOut=sluW;
			AND: tOut=andW;
			_OR: tOut=_orW;
			XOR: tOut=xorW;

			default: tOut=32'b0;

		endcase
	end



	//--------------
	//   Literals
	//--------------

	//ALU control mux literals
	localparam ADD  = 4'b0000;
	localparam SUB  = 4'b0001;
	localparam AND  = 4'b0111;
	localparam _OR  = 4'b1000;
	localparam XOR  = 4'b1001;
	localparam LLS  = 4'b0010;
	localparam LRS  = 4'b0011;
	localparam ARS  = 4'b0100;
	localparam SLT  = 4'b0101;
	localparam SLU  = 4'b0110;


endmodule

src/immGen.v


module immediate_generator (
    input  [31:0] instruction,
    output reg [31:0] imm_out
);

    wire [6:0] opcode;
    assign opcode = instruction[6:0];

    always @(*) begin
        case (opcode)

            // =========================
            // I-TYPE (addi, lw, etc.)
            // imm[11:0] = instruction[31:20]
            // =========================
            7'b0010011, // addi
            7'b0000011: // lw
                imm_out = {{20{instruction[31]}}, instruction[31:20]};

            // =========================
            // S-TYPE (sw)
            // imm[11:5] = instruction[31:25]
            // imm[4:0]  = instruction[11:7]
            // =========================
            7'b0100011: // sw
                imm_out = {{20{instruction[31]}},
                           instruction[31:25],
                           instruction[11:7]};

            // =========================
            // B-TYPE (beq, bne)
            // imm = {instruction[31], instruction[7],
            //        instruction[30:25], instruction[11:8], 0}
            // =========================
            7'b1100011: // branch
                imm_out = {{19{instruction[31]}},
                           instruction[31],
                           instruction[7],
                           instruction[30:25],
                           instruction[11:8],
                           1'b0};

            // =========================
            // U-TYPE (lui, auipc)
            // imm[31:12] = instruction[31:12]
            // =========================
            7'b0110111, // lui
            7'b0010111: // auipc
                imm_out = {instruction[31:12], 12'b0};

            // =========================
            // J-TYPE (jal)
            // imm = {instruction[31], instruction[19:12],
            //        instruction[20], instruction[30:21], 0}
            // =========================
            7'b1101111: // jal
                imm_out = {{11{instruction[31]}},
                           instruction[31],
                           instruction[19:12],
                           instruction[20],
                           instruction[30:21],
                           1'b0};

            // =========================
            // DEFAULT
            // =========================
            default:
                imm_out = 32'b0;
        endcase
    end

endmodule

src/regFile.v
module register_file (
    input clk,
    input reset,
    input regWrite, // De la CU

    input [31:0] instruction, // Instrucción completa
    input [31:0] write_data, // Lo que se escribe en rd

    output reg [31:0] read_data1, // Contenido registro rs1
    output reg [31:0] read_data2 // Contenido registro rs2
);

    reg [31:0] registers [0:31]; // Array de 32 registros, cada uno de 32 bits
    integer i;

    // Extraer campos de la instrucción
    wire [4:0] rs1;
    wire [4:0] rs2;
    wire [4:0] rd;

    assign rs1 = instruction[19:15];
    assign rs2 = instruction[24:20];
    assign rd  = instruction[11:7];

    // Lectura
    always @(*) begin

        if (rs1 == 5'd0)
            read_data1 = 32'b0;
        else
            read_data1 = registers[rs1];

        if (rs2 == 5'd0)
            read_data2 = 32'b0;
        else
            read_data2 = registers[rs2];

    end

    // Escritura y reset
    always @(posedge clk) begin

        if (reset) begin

            for (i = 0; i < 32; i = i + 1)
                registers[i] <= 32'b0;
                registers[2]<=1024;

        end
        else if (regWrite && rd != 5'd0) begin

            registers[rd] <= write_data;

        end

    end

endmodule

src/cUnit.v

//////////////////////////////////////////////////////////////////////////////////
// Company: 
// Engineer: 
// 
// Create Date: 11.05.2026 18:25:04
// Design Name: 
// Module Name: ControlUnit
// Project Name: 
// Target Devices: 
// Tool Versions: 
// Description: 
// 
// Dependencies: 
// 
// Revision:
// Revision 0.01 - File Created
// Additional Comments:
// 
//////////////////////////////////////////////////////////////////////////////////

module ControlUnit(
    input [31:0] instruccion,
   input [3:0] flagsALU, //NZCV

    output reg PCSrc, //jump
   // output reg PCJAL, //Indica que se usa PC+Imm
    output reg MemtoReg, //para Loads
    output reg MemWrite, // para Stores 
    output reg MemRead, //para Loads
    output reg  ALUSrc, // 0 reg, 1 extended imm, upper imm y  PC (tipo J)
    output reg [3:0] ALUControl, //definida en ALU
    output reg RegWrite, // 1 en tipo I, R y Loads
    output reg [1:0] RegSrc, // Es 0 para tipo R, I, S y B, 1 para tipo U  y J (rd bits 11-7) 
    /*aqui los que ocupa el if_stage, si se usan, no se ocupa PCSrc*/
    output reg is_branch, //NU
    output reg is_jal,  //NU
    output reg is_jalr,
    output reg [2:0] branch_op
);


//obtiene las partes de opcode y funct3 y funct7 que se usan en tipo R,I, S y B
//también separa las flags de la ALU
// cond representa si la condición se cumplió o no, para branches
    wire [6:0] opcode;
    wire [2:0] funct3;
    wire [6:0] funct7;
    wire Z;
    wire N;
    wire C;
    wire V;
    reg cond;
   
    assign opcode = instruccion[6:0];
    assign funct3 = instruccion[14:12];
    assign funct7 = instruccion[31:25];
  assign N= flagsALU [1];
   assign Z= flagsALU [0];
    assign C= flagsALU [2];
    assign V= flagsALU [3];

    always @(*) begin
        //Valores por defecto
        MemtoReg = 0; MemWrite = 0; ALUSrc = 0; 
        ALUControl = 4'b0000;  RegWrite = 0; RegSrc=2'd0; 
        MemRead=0; 
        is_branch=0; is_jal =0; is_jalr=0; branch_op=3'b000; PCSrc=0;
        
        
        case (opcode)
        
            7'b0110011: begin // TIPO R
                RegWrite = 1;
                case ({funct7, funct3}) //logica de la ALU
                    {7'b0000000, 3'b000}: ALUControl = 4'b0000; // ADD
                    {7'b0100000, 3'b000}: ALUControl = 4'b0001; // SUB
                    {7'b0000000, 3'b111}: ALUControl = 4'b0111; // AND
                    {7'b0000000, 3'b110}: ALUControl = 4'b1000; // OR
                    {7'b0000000, 3'b100}: ALUControl = 4'b1001; // XOR
                    {7'b0000000, 3'b001}: ALUControl = 4'b0010; // LLS
                    {7'b0000000, 3'b101}: ALUControl = 4'b0011; // LLR
                    {7'b0100000, 3'b101}: ALUControl = 4'b0100; // ARS
                    {7'b0000000, 3'b010}: ALUControl = 4'b0101; // SLT
                    {7'b0000000, 3'b011}: ALUControl = 4'b0110; // SLTU                 
                    default: ALUControl = 3'b000;
                endcase
            end

            7'b0010011: begin // TIPO I 
              RegWrite = 1;ALUSrc = 1;
              case (funct3) //logica de la ALU
                    3'b000: ALUControl = 4'b0000; // ADDI
                    3'b010: ALUControl = 4'b0101; // SLTI
                    3'b011: ALUControl = 4'b0110; // SLTUI
                    3'b100: ALUControl = 4'b1001; // XORI
                    3'b110: ALUControl = 4'b1000; // ORI
                    3'b111: ALUControl = 4'b0111; // ANDI
                    default: ALUControl = 4'b0000;
                endcase
            end

            7'b0000011: begin // LOAD (LW)
                RegWrite = 1;MemRead=1;ALUSrc = 1;MemtoReg = 1; RegSrc=1;
                ALUControl = 4'b0000; // Suma para calcular dirección
            end

            7'b0100011: begin // STORE (SW)
                MemWrite = 1;ALUSrc = 1;
                ALUControl = 4'b0000; // Suma para dirección
            end

            7'b1100011: begin // BRANCH 
                    ALUControl=4'b0001; //resta para comparación
                    is_branch=1;
                    branch_op =funct3;
                    case (funct3) //según condicion
                    3'b101:  // GE
                    cond = ~N|Z;
                    3'b000: //EQ    
                    cond = Z;  
                    3'b001: //NE    
                    cond = ~Z;
                    3'b100: // LT  
                    cond = N^V;                              
                    default: cond = 0;
                    endcase
                PCSrc=cond;
               end
               
            7'b0110111: begin //Lui o tipoU 
            RegWrite=1;RegSrc=2'd3;
            end

            7'b1101111: begin  //tipo J (JAL)
            RegSrc =2'd2;RegWrite=1; is_jal=1;PCSrc=1;
            end
            
            7'b1100111: begin  //tipo J (JALR)                     
            RegSrc =2'd2;RegWrite=1; is_jalr=1;PCSrc=1;
            end
             
            
            default: begin
                // Mantener valores por defecto
            end
        endcase
    end

    



endmodule

src/insMem.v


module instruction_memory(
    input wire [31:0] addr, //Dirección de memoria [31:0] (del PC)
    output reg [31:0] instruction //Instrucción de 32 bits leída [31:0]
    );
    
    reg [31:0] insMem [0:1023];
    initial begin
    $readmemh("./build/program.hex", insMem);
    end
    always @(*) begin 
        instruction=insMem[addr[31:2]];        
    end



    
endmodule

src/bUnit.v

module branch_unit(
    input wire jalr, //indica JALR
    input wire [31:0] pc_current, //PC actual
    input wire [31:0] imm, //extraido de la instrucción
    input wire [31:0] rs1_data,
    output reg [31:0] jump_target
    
    );
    
//Cálculo de direcciones destino  

        
    always @(*) begin
        case(jalr)
            0:jump_target=(pc_current + imm);               //jal/b
            1:jump_target=((rs1_data + imm) & 32'hFFFFFFFE); //jalr
            default:jump_target=(pc_current + imm);
        endcase
    end

    
endmodule

src/pc.v



module program_counter(
    input wire clk,
    input wire reset,
    input wire pc_src, //selector de fuente de próximo PC 
                                //00: PC+4 (secuencial)
                                //01: Jump
    input wire [31:0] jump_target,
    output reg [31:0] pc_out,
    output reg [31:0] pc4
    
    );
    wire [31:0] pc_plus_4;
    assign pc_plus_4 = pc_out + 4; // Incremento secuencial: PC + 4

    reg [31:0] pc_next; // Lógica combinacional para seleccionar próximo PC
    
    always @(*) begin
        case (pc_src)
            1'b0: pc_next = pc_plus_4;      // Secuencial
            1'b1: pc_next = jump_target;  // Jump
            default: pc_next = pc_plus_4;
        endcase
        pc4=pc_plus_4;
    end
    
    // Registro del PC (actualización síncrona)
    always @(posedge clk or posedge reset) begin
        if (reset)
            pc_out <= 32'h00000000;  // Dirección inicial: 0x00000000
        else
            pc_out <= pc_next;
    end
    
endmodule

src/insFetch.v
 

module imStage(
    input wire clk,
    input wire rst,
    input wire jalr,
    input wire jmp,
    input wire [31:0] imm,
    input wire [31:0] rs1,

    output wire [31:0] instruction,
    output wire [31:0] pc4

    );

    wire [31:0] pcOut;
    wire [31:0] jmpTar;

    program_counter PC(
        .clk(clk),
        .reset(rst),
        .pc_src(jmp),
        .jump_target(jmpTar),
        .pc_out(pcOut),
        .pc4(pc4)
    );

    branch_unit BU(
        .jalr(jalr),
        .pc_current(pcOut),
        .imm(imm),
        .rs1_data(rs1),
        .jump_target(jmpTar)
    );

    instruction_memory IM(
        .addr(pcOut),
        .instruction(instruction)
    );

    
endmodule

riscv.v


module riscv(
    input wire clk,
    input wire rst
    );

    wire jalr;
    wire jmp;
    wire [31:0] imm;
    wire [31:0] ins;
    wire [31:0] pc4;

    wire [3:0] aluFlags;
    wire pcSrc;
    wire memToReg;
    wire memWrite;
    wire memRead;
    wire aluSrc;
    wire [3:0] aluControl;
    wire regWrite;
    wire [1:0] regSrc;


    wire [3:0] rs1Addr;
    wire [3:0] rs2Addr;
    wire [3:0] rdAddr;
    reg [31:0] regWriteData;
    wire [31:0] rs1;
    wire [31:0] rs2;

    wire [31:0] aluA;
    wire [31:0] aluB;
    wire [31:0] aluO;

    wire [31:0] memData;


    assign aluA = rs1;
    assign aluB = aluSrc ? imm : rs2;

    //Register write source Mux
    always @(*) begin
        case (regSrc)
            0:regWriteData=aluO;
            1:regWriteData=memData;
            2:regWriteData=pc4;
            3:regWriteData=imm;
            default:regWriteData=0;

        endcase
    end


    //PC Assembly
    imStage s1(
        .clk(clk),
        .rst(rst),
        .jalr(jalr),
        .jmp(jmp),
        .imm(imm),
        .rs1(rs1),

        .instruction(ins),
        .pc4(pc4)

    );


    //Control Unit
    ControlUnit c1(
        .instruccion(ins),
        .flagsALU(aluFlags),

        .PCSrc(jmp),
        .MemtoReg(memToReg),
        .MemWrite(memWrite),
        .MemRead(memRead),
        .ALUSrc(aluSrc),
        .ALUControl(aluControl),
        .RegWrite(regWrite),
        .RegSrc(regSrc),
        .is_jalr(jalr)

    );

    //Register File
    register_file s2(
        .clk(clk),
        .reset(rst),
        .regWrite(regWrite),
        .instruction(ins),
        .write_data(regWriteData),

        .read_data1(rs1),
        .read_data2(rs2)

    );

    //Immediate Generator
    immediate_generator s3(
        .instruction(ins),

        .imm_out(imm)

    );




    //ALU
    ALU s4(
        .inA(aluA),
        .inB(aluB),
        .aluControl(aluControl),

        .result(aluO),
        .zero(aluFlags[0]),
        .carry(aluFlags[2]),
        .negative(aluFlags[1]),
        .overflow(aluFlags[3])

    );

    //Memory File
    memory_io s5(
        .clk(clk),
        .reset(rst),
        .memRead(memRead),
        .memWrite(memWrite),
        .address(aluO),
        .write_data(rs2),
        .ins(ins),

        .read_data(memData)


    );









endmodule

riscvTb.v
`timescale 1ns/1ns

module riscv_tb;

    // ── DUT inputs ──────────────────────────────────────────────
    reg clk;
    reg rst;

    // ── DUT instantiation ────────────────────────────────────────
    riscv uut (
        .clk(clk),
        .rst(rst)
    );

    // ── Clock: 10 ns period (100 MHz) ────────────────────────────
    initial clk = 0;
    always #5 clk = ~clk;

    // ── VCD dump ─────────────────────────────────────────────────
    initial begin
        $dumpfile("signals.vcd");       
        $dumpvars(0, riscv_tb);        
    end

    // ── Reset + run ──────────────────────────────────────────────
    initial begin
        rst = 1;
        @(posedge clk); #1;
        @(posedge clk); #1;
        rst = 0;

        // Run for cycles then stop
        repeat (2000) @(posedge clk);

        $finish;
    end

    // ── Optional: print PC+instruction each cycle ─────────────────
    always @(posedge clk) begin
        if (!rst)
            $display("t=%0t  pc4=%h  ins=%h  regWrite=%b  aluO=%h",
                     $time,
                     uut.pc4,
                     uut.ins,
                     uut.regWrite,
                     uut.aluO);
    end

endmodule

signals.vcd
$date
	Wed Jun 17 10:59:07 2026
$end
$version
	Icarus Verilog
$end
$timescale
	1ns
$end
$scope module riscv_tb $end
$var reg 1 ! clk $end
$var reg 1 " rst $end
$scope module uut $end
$var wire 32 # aluA [31:0] $end
$var wire 1 ! clk $end
$var wire 1 " rst $end
$var wire 32 $ rs2 [31:0] $end
$var wire 32 % rs1 [31:0] $end
$var wire 1 & regWrite $end
$var wire 2 ' regSrc [1:0] $end
$var wire 32 ( pc4 [31:0] $end
$var wire 1 ) memWrite $end
$var wire 1 * memToReg $end
$var wire 1 + memRead $end
$var wire 32 , memData [31:0] $end
$var wire 1 - jmp $end
$var wire 1 . jalr $end
$var wire 32 / ins [31:0] $end
$var wire 32 0 imm [31:0] $end
$var wire 1 1 aluSrc $end
$var wire 32 2 aluO [31:0] $end
$var wire 4 3 aluFlags [3:0] $end
$var wire 4 4 aluControl [3:0] $end
$var wire 32 5 aluB [31:0] $end
$var reg 32 6 regWriteData [31:0] $end
$scope module c1 $end
$var wire 4 7 flagsALU [3:0] $end
$var wire 7 8 opcode [6:0] $end
$var wire 32 9 instruccion [31:0] $end
$var wire 7 : funct7 [6:0] $end
$var wire 3 ; funct3 [2:0] $end
$var wire 1 < Z $end
$var wire 1 = V $end
$var wire 1 > N $end
$var wire 1 ? C $end
$var reg 4 @ ALUControl [3:0] $end
$var reg 1 1 ALUSrc $end
$var reg 1 + MemRead $end
$var reg 1 ) MemWrite $end
$var reg 1 * MemtoReg $end
$var reg 1 - PCSrc $end
$var reg 2 A RegSrc [1:0] $end
$var reg 1 & RegWrite $end
$var reg 3 B branch_op [2:0] $end
$var reg 1 C cond $end
$var reg 1 D is_branch $end
$var reg 1 E is_jal $end
$var reg 1 . is_jalr $end
$upscope $end
$scope module s1 $end
$var wire 1 ! clk $end
$var wire 1 . jalr $end
$var wire 1 - jmp $end
$var wire 1 " rst $end
$var wire 32 F rs1 [31:0] $end
$var wire 32 G pcOut [31:0] $end
$var wire 32 H pc4 [31:0] $end
$var wire 32 I jmpTar [31:0] $end
$var wire 32 J instruction [31:0] $end
$var wire 32 K imm [31:0] $end
$scope module BU $end
$var wire 1 . jalr $end
$var wire 32 L rs1_data [31:0] $end
$var wire 32 M pc_current [31:0] $end
$var wire 32 N imm [31:0] $end
$var reg 32 O jump_target [31:0] $end
$upscope $end
$scope module IM $end
$var wire 32 P addr [31:0] $end
$var reg 32 Q instruction [31:0] $end
$upscope $end
$scope module PC $end
$var wire 1 ! clk $end
$var wire 32 R jump_target [31:0] $end
$var wire 1 - pc_src $end
$var wire 1 " reset $end
$var wire 32 S pc_plus_4 [31:0] $end
$var reg 32 T pc4 [31:0] $end
$var reg 32 U pc_next [31:0] $end
$var reg 32 V pc_out [31:0] $end
$upscope $end
$upscope $end
$scope module s2 $end
$var wire 1 ! clk $end
$var wire 32 W instruction [31:0] $end
$var wire 1 & regWrite $end
$var wire 1 " reset $end
$var wire 32 X write_data [31:0] $end
$var wire 5 Y rs2 [4:0] $end
$var wire 5 Z rs1 [4:0] $end
$var wire 5 [ rd [4:0] $end
$var reg 32 \ read_data1 [31:0] $end
$var reg 32 ] read_data2 [31:0] $end
$var integer 32 ^ i [31:0] $end
$upscope $end
$scope module s3 $end
$var wire 32 _ instruction [31:0] $end
$var wire 7 ` opcode [6:0] $end
$var reg 32 a imm_out [31:0] $end
$upscope $end
$scope module s4 $end
$var wire 32 b _orW [31:0] $end
$var wire 4 c aluControl [3:0] $end
$var wire 32 d andW [31:0] $end
$var wire 1 e carry $end
$var wire 32 f inA [31:0] $end
$var wire 32 g inB [31:0] $end
$var wire 32 h xorW [31:0] $end
$var wire 1 i zero $end
$var wire 32 j sumW [31:0] $end
$var wire 32 k subW [31:0] $end
$var wire 32 l sluW [31:0] $end
$var wire 32 m sltW [31:0] $end
$var wire 32 n result [31:0] $end
$var wire 1 o overflow $end
$var wire 1 p negative $end
$var wire 32 q lrsW [31:0] $end
$var wire 32 r llsW [31:0] $end
$var wire 32 s arsW [31:0] $end
$var parameter 4 t ADD $end
$var parameter 4 u AND $end
$var parameter 4 v ARS $end
$var parameter 4 w LLS $end
$var parameter 4 x LRS $end
$var parameter 4 y SLT $end
$var parameter 4 z SLU $end
$var parameter 4 { SUB $end
$var parameter 4 | XOR $end
$var parameter 4 } _OR $end
$var reg 32 ~ tOut [31:0] $end
$upscope $end
$scope module s5 $end
$var wire 32 !" address [31:0] $end
$var wire 1 ! clk $end
$var wire 32 "" ins [31:0] $end
$var wire 1 + memRead $end
$var wire 1 ) memWrite $end
$var wire 1 " reset $end
$var wire 32 #" write_data [31:0] $end
$var reg 32 $" read_data [31:0] $end
$var integer 32 %" fd [31:0] $end
$var integer 32 &" i [31:0] $end
$upscope $end
$upscope $end
$upscope $end
$enddefinitions $end
$comment Show the parameter values. $end
$dumpall
b1000 }
b1001 |
b1 {
b110 z
b101 y
b11 x
b10 w
b100 v
b111 u
b0 t
$end
#0
$dumpvars
bx &"
bx %"
b0 $"
b0 #"
b11111110000000010000000100010011 ""
bx !"
bx ~
bx s
bx r
bx q
xp
xo
bx n
b0x m
b0x l
bx k
bx j
xi
bx h
b11111111111111111111111111100000 g
bx f
0e
bx00000 d
b0 c
b111111111111111111111111111xxxxx b
b11111111111111111111111111100000 a
b10011 `
b11111110000000010000000100010011 _
bx ^
b0 ]
bx \
b10 [
b10 Z
b0 Y
bx X
b11111110000000010000000100010011 W
b0 V
b100 U
b100 T
b100 S
b11111111111111111111111111100000 R
b11111110000000010000000100010011 Q
b0 P
b11111111111111111111111111100000 O
b11111111111111111111111111100000 N
b0 M
bx L
b11111111111111111111111111100000 K
b11111110000000010000000100010011 J
b11111111111111111111111111100000 I
b100 H
b0 G
bx F
0E
0D
xC
b0 B
b0 A
b0 @
0?
x>
x=
x<
b0 ;
b1111111 :
b11111110000000010000000100010011 9
b10011 8
bx0xx 7
bx 6
b11111111111111111111111111100000 5
b0 4
bx0xx 3
bx 2
11
b11111111111111111111111111100000 0
b11111110000000010000000100010011 /
0.
0-
b0 ,
0+
0*
0)
b100 (
b0 '
1&
bx %
b0 $
bx #
1"
0!
$end
#5
0=
0o
1&
11
b1111100000 6
b1111100000 X
0<
0>
b1111100000 2
b1111100000 n
b1111100000 !"
0i
b0 3
b0 7
0p
b10000000000 d
b11111111111111111111111111100000 b
b11111111111111111111101111100000 h
b1111100000 ~
b0 m
b1 l
b1111100000 j
b10000100000 k
b10000000000 r
b10000000000 q
b10000000000 s
b10000000000 #
b10000000000 f
b10000000000 %
b10000000000 F
b10000000000 L
b10000000000 \
b100000 ^
b100000000 &"
1!
#10
0!
#15
b100000000 &"
b100000 ^
1!
#16
0"
#20
0!
#25
b1111111100 b
b0 l
b1111111100 6
b1111111100 X
1)
0&
11
b11100 5
b11100 g
b1111111100 2
b1111111100 n
b1111111100 !"
b1 Y
b11100 [
b100011 `
b0 :
b10 ;
b100011 8
b11100 0
b11100 K
b11100 N
b11100 a
b0 d
b1111111100 h
b1111111100 ~
b1000 (
b1000 H
b1000 T
b1000 U
b100000 I
b100000 O
b100000 R
b100010010111000100011 /
b100010010111000100011 9
b100010010111000100011 J
b100010010111000100011 Q
b100010010111000100011 W
b100010010111000100011 _
b100010010111000100011 ""
b1111111100 j
b1111000100 k
b0 r
b0 q
b0 s
b1111100000 #
b1111100000 f
b1111100000 %
b1111100000 F
b1111100000 L
b1111100000 \
b1000 S
b100 G
b100 M
b100 P
b100 V
1!
#30
0!
#35
b1111111000 6
b1111111000 X
b1111111000 2
b1111111000 n
b1111111000 !"
b1111111000 b
b1111111000 h
b1111111000 ~
b11100000000000000000000000000000 r
b1111111000 j
b1111001000 k
b11000 5
b11000 g
b1000 Y
b11000 [
b11000 0
b11000 K
b11000 N
b11000 a
b1100 (
b1100 H
b1100 T
b1100 U
b100000 I
b100000 O
b100000 R
b100000010010110000100011 /
b100000010010110000100011 9
b100000010010110000100011 J
b100000010010110000100011 Q
b100000010010110000100011 W
b100000010010110000100011 _
b100000010010110000100011 ""
b1100 S
b1000 G
b1000 M
b1000 P
b1000 V
1!
#40
0!
#45
b10000000000 6
b10000000000 X
b10000000000 2
b10000000000 n
b10000000000 !"
b100000 d
b1111100000 b
b1111000000 h
b10000000000 ~
b1111100000 r
b1111100000 q
b1111100000 s
1&
11
0)
b10000000000 j
b1111000000 k
b100000 5
b100000 g
b0 Y
b1000 [
b10011 `
b1 :
b0 ;
b10011 8
b100000 0
b100000 K
b100000 N
b100000 a
b10000 (
b10000 H
b10000 T
b10000 U
b101100 I
b101100 O
b101100 R
b10000000010000010000010011 /
b10000000010000010000010011 9
b10000000010000010000010011 J
b10000000010000010000010011 Q
b10000000010000010000010011 W
b10000000010000010000010011 _
b10000000010000010000010011 ""
b10000 S
b1100 G
b1100 M
b1100 P
b1100 V
1!
#50
0!
#55
b1111100000 2
b1111100000 n
b1111100000 !"
b10000000000000000 6
b10000000000000000 X
b0 d
b1111100000 h
b1111100000 ~
b11 '
b11 A
1&
01
b1111100000 j
b1111100000 k
b0 5
b0 g
b1111 [
b110111 `
b0 :
b110111 8
b10000000000000000 0
b10000000000000000 K
b10000000000000000 N
b10000000000000000 a
b10100 (
b10100 H
b10100 T
b10100 U
b10000000000010000 I
b10000000000010000 O
b10000000000010000 R
b10000011110110111 /
b10000011110110111 9
b10000011110110111 J
b10000011110110111 Q
b10000011110110111 W
b10000011110110111 _
b10000011110110111 ""
b10100 S
b10000 G
b10000 M
b10000 P
b10000 V
1!
#60
0!
#65
b10000011110101100 2
b10000011110101100 n
b10000011110101100 !"
b10000011110101100 b
b10000011110101100 h
b10000011110101100 ~
b11110101100 5
b11110101100 g
b10000011110101100 j
b1111100001010100 k
b10000000000000000000000000000 r
b10000 q
b10000 s
b10000000000000000 #
b10000000000000000 f
b10000000000000000 %
b10000000000000000 F
b10000000000000000 L
b10000000000000000 \
11
b0 '
b0 A
1&
b10000011110101100 6
b10000011110101100 X
b1111 Z
b1100 Y
b10011 `
b111101 :
b10011 8
b11110101100 0
b11110101100 K
b11110101100 N
b11110101100 a
b11000 (
b11000 H
b11000 T
b11000 U
b11111000000 I
b11111000000 O
b11111000000 R
b1111010110001111000011110010011 /
b1111010110001111000011110010011 9
b1111010110001111000011110010011 J
b1111010110001111000011110010011 Q
b1111010110001111000011110010011 W
b1111010110001111000011110010011 _
b1111010110001111000011110010011 ""
b11000 S
b10100 G
b10100 M
b10100 P
b10100 V
1!
#70
0!
#75
b11111111111111111111111111101100 b
b1 l
b1111101100 6
b1111101100 X
b10000011110101100 $
b10000011110101100 ]
b10000011110101100 #"
b0 q
b0 s
1)
0&
11
b11111111111111111111111111101100 5
b11111111111111111111111111101100 g
b1111101100 2
b1111101100 n
b1111101100 !"
b1000 Z
b1111 Y
b1100 [
b100011 `
b1111111 :
b10 ;
b100011 8
b11111111111111111111111111101100 0
b11111111111111111111111111101100 K
b11111111111111111111111111101100 N
b11111111111111111111111111101100 a
b10000000000 d
b11111111111111111111101111101100 h
b1111101100 ~
b11100 (
b11100 H
b11100 T
b11100 U
b100 I
b100 O
b100 R
b11111110111101000010011000100011 /
b11111110111101000010011000100011 9
b11111110111101000010011000100011 J
b11111110111101000010011000100011 Q
b11111110111101000010011000100011 W
b11111110111101000010011000100011 _
b11111110111101000010011000100011 ""
b1111101100 j
b10000010100 k
b10000000000000000000000 r
b10000000000 #
b10000000000 f
b10000000000 %
b10000000000 F
b10000000000 L
b10000000000 \
b11100 S
b11000 G
b11000 M
b11000 P
b11000 V
1!
#80
0!
#85
b1111101000 6
b1111101000 X
b1111101000 2
b1111101000 n
b1111101000 !"
b11111111111111111111111111101000 b
b11111111111111111111101111101000 h
b1111101000 ~
b1000000000000000000 r
b100 q
b100 s
b0 $
b0 ]
b0 #"
b1111101000 j
b10000011000 k
b11111111111111111111111111101000 5
b11111111111111111111111111101000 g
b0 Y
b1000 [
b11111111111111111111111111101000 0
b11111111111111111111111111101000 K
b11111111111111111111111111101000 N
b11111111111111111111111111101000 a
b100000 (
b100000 H
b100000 T
b100000 U
b100 I
b100 O
b100 R
b11111110000001000010010000100011 /
b11111110000001000010010000100011 9
b11111110000001000010010000100011 J
b11111110000001000010010000100011 Q
b11111110000001000010010000100011 W
b11111110000001000010010000100011 _
b11111110000001000010010000100011 ""
b100000 S
b11100 G
b11100 M
b11100 P
b11100 V
1!
#90
0!
#95
1<
b1 3
b1 7
1i
b0 l
b0 2
b0 n
b0 !"
b100100 6
b100100 X
b0 d
b0 b
b0 h
b0 ~
b0 r
b0 q
b0 s
b0 #
b0 f
b0 %
b0 F
b0 L
b0 \
1-
1E
1&
b10 '
b10 A
01
0)
b0 j
b0 k
b0 5
b0 g
b0 Z
b100 Y
b0 [
b1101111 `
b1 :
b0 ;
b1101111 8
b100100 0
b100100 K
b100100 N
b100100 a
b100100 (
b100100 H
b100100 T
b1000100 U
b1000100 I
b1000100 O
b1000100 R
b10010000000000000001101111 /
b10010000000000000001101111 9
b10010000000000000001101111 J
b10010000000000000001101111 Q
b10010000000000000001101111 W
b10010000000000000001101111 _
b10010000000000000001101111 ""
b100100 S
b100000 G
b100000 M
b100000 P
b100000 V
1!
#100
0!
